{
  "name": "vault_spider_0003",
  "size": [
    38,
    19
  ],
  "orient": "float",
  "categories": [
    "ported"
  ],
  "themes": [
    "dungeon",
    "spider"
  ],
  "floor_range": [
    1,
    10
  ],
  "weight": 20,
  "tags": [],
  "grid": [
    "                xxx                   ",
    "               xxxxxxxxx              ",
    "             xxx.......xxx            ",
    "          xxxx...........xxxxxx       ",
    "     xx  xx.....6......4......xxx     ",
    "    xxxxxx...6.6.6....44........x     ",
    "   xxxx.....6.66...3........54..xx    ",
    "  xx....6.6.6...4...47.......4...xx   ",
    " xx......6.....4........47...4....xx  ",
    "xxx...5....3.474...3.....4..5.....x.  ",
    " xx.............4....575......4...xx  ",
    " xx...............575.............xx..",
    "  xx.......444................66..x.4 ",
    "   xx................5.....666....x...",
    "   xx.....444..........4......6.6x.45.",
    "    xxxx.....................6.6.4... ",
    "       xxxxx.xxx....xx....xx....4..4. ",
    "        xx xxx xxxxxxxxxxxxxxx.x.4..  ",
    "           x       xx        xxx 4    "
  ],
  "spawns": {
    "3": {
      "enemy_pool": [
        "orb_spider",
        "redback"
      ]
    }
  },
  "_original_dcss_id": "des_grunt_spider_rune_circles"
}